{
  "duplicate_of": {
    "Public Api.Artifact.__eq__": "Public Api.Api.__eq__",
    "Public Api.Artifact.__ge__": "Public Api.Api.__ge__",
    "Public Api.Artifact.__gt__": "Public Api.Api.__gt__",
    "Public Api.Artifact.__le__": "Public Api.Api.__le__",
    "Public Api.Artifact.__lt__": "Public Api.Api.__lt__",
    "Public Api.Artifact.__ne__": "Public Api.Api.__ne__",
    "Public Api.Artifact.__new__": "Public Api.Api.__new__",
    "Public Api.ArtifactCollection.__eq__": "Public Api.Api.__eq__",
    "Public Api.ArtifactCollection.__ge__": "Public Api.Api.__ge__",
    "Public Api.ArtifactCollection.__gt__": "Public Api.Api.__gt__",
    "Public Api.ArtifactCollection.__le__": "Public Api.Api.__le__",
    "Public Api.ArtifactCollection.__lt__": "Public Api.Api.__lt__",
    "Public Api.ArtifactCollection.__ne__": "Public Api.Api.__ne__",
    "Public Api.ArtifactCollection.__new__": "Public Api.Api.__new__",
    "Public Api.ArtifactType.__eq__": "Public Api.Api.__eq__",
    "Public Api.ArtifactType.__ge__": "Public Api.Api.__ge__",
    "Public Api.ArtifactType.__gt__": "Public Api.Api.__gt__",
    "Public Api.ArtifactType.__le__": "Public Api.Api.__le__",
    "Public Api.ArtifactType.__lt__": "Public Api.Api.__lt__",
    "Public Api.ArtifactType.__ne__": "Public Api.Api.__ne__",
    "Public Api.ArtifactType.__new__": "Public Api.Api.__new__",
    "Public Api.ArtifactVersions.__eq__": "Public Api.Api.__eq__",
    "Public Api.ArtifactVersions.__ge__": "Public Api.Api.__ge__",
    "Public Api.ArtifactVersions.__gt__": "Public Api.Api.__gt__",
    "Public Api.ArtifactVersions.__le__": "Public Api.Api.__le__",
    "Public Api.ArtifactVersions.__lt__": "Public Api.Api.__lt__",
    "Public Api.ArtifactVersions.__ne__": "Public Api.Api.__ne__",
    "Public Api.ArtifactVersions.__new__": "Public Api.Api.__new__",
    "Public Api.BetaReport.__eq__": "Public Api.Api.__eq__",
    "Public Api.BetaReport.__ge__": "Public Api.Api.__ge__",
    "Public Api.BetaReport.__gt__": "Public Api.Api.__gt__",
    "Public Api.BetaReport.__le__": "Public Api.Api.__le__",
    "Public Api.BetaReport.__lt__": "Public Api.Api.__lt__",
    "Public Api.BetaReport.__ne__": "Public Api.Api.__ne__",
    "Public Api.BetaReport.__new__": "Public Api.Api.__new__",
    "Public Api.File.__eq__": "Public Api.Api.__eq__",
    "Public Api.File.__ge__": "Public Api.Api.__ge__",
    "Public Api.File.__gt__": "Public Api.Api.__gt__",
    "Public Api.File.__le__": "Public Api.Api.__le__",
    "Public Api.File.__lt__": "Public Api.Api.__lt__",
    "Public Api.File.__ne__": "Public Api.Api.__ne__",
    "Public Api.File.__new__": "Public Api.Api.__new__",
    "Public Api.Files.__eq__": "Public Api.Api.__eq__",
    "Public Api.Files.__ge__": "Public Api.Api.__ge__",
    "Public Api.Files.__getitem__": "Public Api.ArtifactVersions.__getitem__",
    "Public Api.Files.__gt__": "Public Api.Api.__gt__",
    "Public Api.Files.__iter__": "Public Api.ArtifactVersions.__iter__",
    "Public Api.Files.__le__": "Public Api.Api.__le__",
    "Public Api.Files.__len__": "Public Api.ArtifactVersions.__len__",
    "Public Api.Files.__lt__": "Public Api.Api.__lt__",
    "Public Api.Files.__ne__": "Public Api.Api.__ne__",
    "Public Api.Files.__new__": "Public Api.Api.__new__",
    "Public Api.Files.next": "Public Api.ArtifactVersions.next",
    "Public Api.Project.__eq__": "Public Api.Api.__eq__",
    "Public Api.Project.__ge__": "Public Api.Api.__ge__",
    "Public Api.Project.__gt__": "Public Api.Api.__gt__",
    "Public Api.Project.__le__": "Public Api.Api.__le__",
    "Public Api.Project.__lt__": "Public Api.Api.__lt__",
    "Public Api.Project.__ne__": "Public Api.Api.__ne__",
    "Public Api.Project.__new__": "Public Api.Api.__new__",
    "Public Api.Project.snake_to_camel": "Public Api.BetaReport.snake_to_camel",
    "Public Api.Projects.__eq__": "Public Api.Api.__eq__",
    "Public Api.Projects.__ge__": "Public Api.Api.__ge__",
    "Public Api.Projects.__getitem__": "Public Api.ArtifactVersions.__getitem__",
    "Public Api.Projects.__gt__": "Public Api.Api.__gt__",
    "Public Api.Projects.__iter__": "Public Api.ArtifactVersions.__iter__",
    "Public Api.Projects.__le__": "Public Api.Api.__le__",
    "Public Api.Projects.__len__": "Public Api.ArtifactVersions.__len__",
    "Public Api.Projects.__lt__": "Public Api.Api.__lt__",
    "Public Api.Projects.__ne__": "Public Api.Api.__ne__",
    "Public Api.Projects.__new__": "Public Api.Api.__new__",
    "Public Api.Projects.next": "Public Api.ArtifactVersions.next",
    "Public Api.Projects.update_variables": "Public Api.ArtifactVersions.update_variables",
    "Public Api.QueryGenerator.__eq__": "Public Api.Api.__eq__",
    "Public Api.QueryGenerator.__ge__": "Public Api.Api.__ge__",
    "Public Api.QueryGenerator.__gt__": "Public Api.Api.__gt__",
    "Public Api.QueryGenerator.__le__": "Public Api.Api.__le__",
    "Public Api.QueryGenerator.__lt__": "Public Api.Api.__lt__",
    "Public Api.QueryGenerator.__ne__": "Public Api.Api.__ne__",
    "Public Api.QueryGenerator.__new__": "Public Api.Api.__new__",
    "Public Api.Reports.__eq__": "Public Api.Api.__eq__",
    "Public Api.Reports.__ge__": "Public Api.Api.__ge__",
    "Public Api.Reports.__getitem__": "Public Api.ArtifactVersions.__getitem__",
    "Public Api.Reports.__gt__": "Public Api.Api.__gt__",
    "Public Api.Reports.__iter__": "Public Api.ArtifactVersions.__iter__",
    "Public Api.Reports.__le__": "Public Api.Api.__le__",
    "Public Api.Reports.__len__": "Public Api.ArtifactVersions.__len__",
    "Public Api.Reports.__lt__": "Public Api.Api.__lt__",
    "Public Api.Reports.__ne__": "Public Api.Api.__ne__",
    "Public Api.Reports.__new__": "Public Api.Api.__new__",
    "Public Api.Reports.next": "Public Api.ArtifactVersions.next",
    "Public Api.Run.__eq__": "Public Api.Api.__eq__",
    "Public Api.Run.__ge__": "Public Api.Api.__ge__",
    "Public Api.Run.__gt__": "Public Api.Api.__gt__",
    "Public Api.Run.__le__": "Public Api.Api.__le__",
    "Public Api.Run.__lt__": "Public Api.Api.__lt__",
    "Public Api.Run.__ne__": "Public Api.Api.__ne__",
    "Public Api.Run.__new__": "Public Api.Api.__new__",
    "Public Api.Run.snake_to_camel": "Public Api.BetaReport.snake_to_camel",
    "Public Api.Runs.__eq__": "Public Api.Api.__eq__",
    "Public Api.Runs.__ge__": "Public Api.Api.__ge__",
    "Public Api.Runs.__getitem__": "Public Api.ArtifactVersions.__getitem__",
    "Public Api.Runs.__gt__": "Public Api.Api.__gt__",
    "Public Api.Runs.__iter__": "Public Api.ArtifactVersions.__iter__",
    "Public Api.Runs.__le__": "Public Api.Api.__le__",
    "Public Api.Runs.__len__": "Public Api.ArtifactVersions.__len__",
    "Public Api.Runs.__lt__": "Public Api.Api.__lt__",
    "Public Api.Runs.__ne__": "Public Api.Api.__ne__",
    "Public Api.Runs.__new__": "Public Api.Api.__new__",
    "Public Api.Runs.next": "Public Api.ArtifactVersions.next",
    "Public Api.Runs.update_variables": "Public Api.ArtifactVersions.update_variables",
    "Public Api.Sweep.__eq__": "Public Api.Api.__eq__",
    "Public Api.Sweep.__ge__": "Public Api.Api.__ge__",
    "Public Api.Sweep.__gt__": "Public Api.Api.__gt__",
    "Public Api.Sweep.__le__": "Public Api.Api.__le__",
    "Public Api.Sweep.__lt__": "Public Api.Api.__lt__",
    "Public Api.Sweep.__ne__": "Public Api.Api.__ne__",
    "Public Api.Sweep.__new__": "Public Api.Api.__new__",
    "Public Api.Sweep.snake_to_camel": "Public Api.BetaReport.snake_to_camel"
  },
  "is_fragment": {
    "Public Api": false,
    "Public Api.Api": false,
    "Public Api.Api.VIEWER_QUERY": true,
    "Public Api.Api.__eq__": true,
    "Public Api.Api.__ge__": true,
    "Public Api.Api.__gt__": true,
    "Public Api.Api.__init__": true,
    "Public Api.Api.__le__": true,
    "Public Api.Api.__lt__": true,
    "Public Api.Api.__ne__": true,
    "Public Api.Api.__new__": true,
    "Public Api.Api.api_key": true,
    "Public Api.Api.artifact": true,
    "Public Api.Api.artifact_type": true,
    "Public Api.Api.artifact_types": true,
    "Public Api.Api.artifact_versions": true,
    "Public Api.Api.client": true,
    "Public Api.Api.create_run": true,
    "Public Api.Api.default_entity": true,
    "Public Api.Api.flush": true,
    "Public Api.Api.projects": true,
    "Public Api.Api.reports": true,
    "Public Api.Api.run": true,
    "Public Api.Api.runs": true,
    "Public Api.Api.sweep": true,
    "Public Api.Api.user_agent": true,
    "Public Api.Artifact": false,
    "Public Api.Artifact.QUERY": true,
    "Public Api.Artifact.__eq__": true,
    "Public Api.Artifact.__ge__": true,
    "Public Api.Artifact.__gt__": true,
    "Public Api.Artifact.__init__": true,
    "Public Api.Artifact.__le__": true,
    "Public Api.Artifact.__lt__": true,
    "Public Api.Artifact.__ne__": true,
    "Public Api.Artifact.__new__": true,
    "Public Api.Artifact.add_dir": true,
    "Public Api.Artifact.add_file": true,
    "Public Api.Artifact.add_reference": true,
    "Public Api.Artifact.aliases": true,
    "Public Api.Artifact.created_at": true,
    "Public Api.Artifact.delete": true,
    "Public Api.Artifact.description": true,
    "Public Api.Artifact.digest": true,
    "Public Api.Artifact.download": true,
    "Public Api.Artifact.expected_type": true,
    "Public Api.Artifact.file": true,
    "Public Api.Artifact.from_id": true,
    "Public Api.Artifact.get": true,
    "Public Api.Artifact.get_path": true,
    "Public Api.Artifact.id": true,
    "Public Api.Artifact.logged_by": true,
    "Public Api.Artifact.manifest": true,
    "Public Api.Artifact.metadata": true,
    "Public Api.Artifact.name": true,
    "Public Api.Artifact.new_file": true,
    "Public Api.Artifact.save": true,
    "Public Api.Artifact.size": true,
    "Public Api.Artifact.state": true,
    "Public Api.Artifact.type": true,
    "Public Api.Artifact.updated_at": true,
    "Public Api.Artifact.used_by": true,
    "Public Api.Artifact.verify": true,
    "Public Api.ArtifactCollection": false,
    "Public Api.ArtifactCollection.__eq__": true,
    "Public Api.ArtifactCollection.__ge__": true,
    "Public Api.ArtifactCollection.__gt__": true,
    "Public Api.ArtifactCollection.__init__": true,
    "Public Api.ArtifactCollection.__le__": true,
    "Public Api.ArtifactCollection.__lt__": true,
    "Public Api.ArtifactCollection.__ne__": true,
    "Public Api.ArtifactCollection.__new__": true,
    "Public Api.ArtifactCollection.id": true,
    "Public Api.ArtifactCollection.versions": true,
    "Public Api.ArtifactType": false,
    "Public Api.ArtifactType.__eq__": true,
    "Public Api.ArtifactType.__ge__": true,
    "Public Api.ArtifactType.__gt__": true,
    "Public Api.ArtifactType.__init__": true,
    "Public Api.ArtifactType.__le__": true,
    "Public Api.ArtifactType.__lt__": true,
    "Public Api.ArtifactType.__ne__": true,
    "Public Api.ArtifactType.__new__": true,
    "Public Api.ArtifactType.collection": true,
    "Public Api.ArtifactType.collections": true,
    "Public Api.ArtifactType.id": true,
    "Public Api.ArtifactType.load": true,
    "Public Api.ArtifactType.name": true,
    "Public Api.ArtifactVersions": false,
    "Public Api.ArtifactVersions.QUERY": true,
    "Public Api.ArtifactVersions.__eq__": true,
    "Public Api.ArtifactVersions.__ge__": true,
    "Public Api.ArtifactVersions.__getitem__": true,
    "Public Api.ArtifactVersions.__gt__": true,
    "Public Api.ArtifactVersions.__init__": true,
    "Public Api.ArtifactVersions.__iter__": true,
    "Public Api.ArtifactVersions.__le__": true,
    "Public Api.ArtifactVersions.__len__": true,
    "Public Api.ArtifactVersions.__lt__": true,
    "Public Api.ArtifactVersions.__ne__": true,
    "Public Api.ArtifactVersions.__new__": true,
    "Public Api.ArtifactVersions.convert_objects": true,
    "Public Api.ArtifactVersions.cursor": true,
    "Public Api.ArtifactVersions.length": true,
    "Public Api.ArtifactVersions.more": true,
    "Public Api.ArtifactVersions.next": true,
    "Public Api.ArtifactVersions.update_variables": true,
    "Public Api.BetaReport": false,
    "Public Api.BetaReport.__eq__": true,
    "Public Api.BetaReport.__ge__": true,
    "Public Api.BetaReport.__gt__": true,
    "Public Api.BetaReport.__init__": true,
    "Public Api.BetaReport.__le__": true,
    "Public Api.BetaReport.__lt__": true,
    "Public Api.BetaReport.__ne__": true,
    "Public Api.BetaReport.__new__": true,
    "Public Api.BetaReport.runs": true,
    "Public Api.BetaReport.sections": true,
    "Public Api.BetaReport.snake_to_camel": true,
    "Public Api.BetaReport.updated_at": true,
    "Public Api.File": false,
    "Public Api.File.__eq__": true,
    "Public Api.File.__ge__": true,
    "Public Api.File.__gt__": true,
    "Public Api.File.__init__": true,
    "Public Api.File.__le__": true,
    "Public Api.File.__lt__": true,
    "Public Api.File.__ne__": true,
    "Public Api.File.__new__": true,
    "Public Api.File.delete": true,
    "Public Api.File.digest": true,
    "Public Api.File.direct_url": true,
    "Public Api.File.download": true,
    "Public Api.File.id": true,
    "Public Api.File.md5": true,
    "Public Api.File.mimetype": true,
    "Public Api.File.name": true,
    "Public Api.File.size": true,
    "Public Api.File.updated_at": true,
    "Public Api.File.url": true,
    "Public Api.Files": false,
    "Public Api.Files.QUERY": true,
    "Public Api.Files.__eq__": true,
    "Public Api.Files.__ge__": true,
    "Public Api.Files.__getitem__": true,
    "Public Api.Files.__gt__": true,
    "Public Api.Files.__init__": true,
    "Public Api.Files.__iter__": true,
    "Public Api.Files.__le__": true,
    "Public Api.Files.__len__": true,
    "Public Api.Files.__lt__": true,
    "Public Api.Files.__ne__": true,
    "Public Api.Files.__new__": true,
    "Public Api.Files.convert_objects": true,
    "Public Api.Files.cursor": true,
    "Public Api.Files.length": true,
    "Public Api.Files.more": true,
    "Public Api.Files.next": true,
    "Public Api.Files.update_variables": true,
    "Public Api.Project": false,
    "Public Api.Project.__eq__": true,
    "Public Api.Project.__ge__": true,
    "Public Api.Project.__gt__": true,
    "Public Api.Project.__init__": true,
    "Public Api.Project.__le__": true,
    "Public Api.Project.__lt__": true,
    "Public Api.Project.__ne__": true,
    "Public Api.Project.__new__": true,
    "Public Api.Project.artifacts_types": true,
    "Public Api.Project.path": true,
    "Public Api.Project.snake_to_camel": true,
    "Public Api.Projects": false,
    "Public Api.Projects.QUERY": true,
    "Public Api.Projects.__eq__": true,
    "Public Api.Projects.__ge__": true,
    "Public Api.Projects.__getitem__": true,
    "Public Api.Projects.__gt__": true,
    "Public Api.Projects.__init__": true,
    "Public Api.Projects.__iter__": true,
    "Public Api.Projects.__le__": true,
    "Public Api.Projects.__len__": true,
    "Public Api.Projects.__lt__": true,
    "Public Api.Projects.__ne__": true,
    "Public Api.Projects.__new__": true,
    "Public Api.Projects.convert_objects": true,
    "Public Api.Projects.cursor": true,
    "Public Api.Projects.length": true,
    "Public Api.Projects.more": true,
    "Public Api.Projects.next": true,
    "Public Api.Projects.update_variables": true,
    "Public Api.QueryGenerator": false,
    "Public Api.QueryGenerator.GROUP_OP_TO_MONGO": true,
    "Public Api.QueryGenerator.INDIVIDUAL_OP_TO_MONGO": true,
    "Public Api.QueryGenerator.__eq__": true,
    "Public Api.QueryGenerator.__ge__": true,
    "Public Api.QueryGenerator.__gt__": true,
    "Public Api.QueryGenerator.__init__": true,
    "Public Api.QueryGenerator.__le__": true,
    "Public Api.QueryGenerator.__lt__": true,
    "Public Api.QueryGenerator.__ne__": true,
    "Public Api.QueryGenerator.__new__": true,
    "Public Api.QueryGenerator.filter_to_mongo": true,
    "Public Api.QueryGenerator.format_order_key": true,
    "Public Api.QueryGenerator.key_to_server_path": true,
    "Public Api.Reports": false,
    "Public Api.Reports.QUERY": true,
    "Public Api.Reports.__eq__": true,
    "Public Api.Reports.__ge__": true,
    "Public Api.Reports.__getitem__": true,
    "Public Api.Reports.__gt__": true,
    "Public Api.Reports.__init__": true,
    "Public Api.Reports.__iter__": true,
    "Public Api.Reports.__le__": true,
    "Public Api.Reports.__len__": true,
    "Public Api.Reports.__lt__": true,
    "Public Api.Reports.__ne__": true,
    "Public Api.Reports.__new__": true,
    "Public Api.Reports.convert_objects": true,
    "Public Api.Reports.cursor": true,
    "Public Api.Reports.length": true,
    "Public Api.Reports.more": true,
    "Public Api.Reports.next": true,
    "Public Api.Reports.update_variables": true,
    "Public Api.Run": false,
    "Public Api.Run.__eq__": true,
    "Public Api.Run.__ge__": true,
    "Public Api.Run.__gt__": true,
    "Public Api.Run.__init__": true,
    "Public Api.Run.__le__": true,
    "Public Api.Run.__lt__": true,
    "Public Api.Run.__ne__": true,
    "Public Api.Run.__new__": true,
    "Public Api.Run.create": true,
    "Public Api.Run.delete": true,
    "Public Api.Run.entity": true,
    "Public Api.Run.file": true,
    "Public Api.Run.files": true,
    "Public Api.Run.history": true,
    "Public Api.Run.id": true,
    "Public Api.Run.json_config": true,
    "Public Api.Run.lastHistoryStep": true,
    "Public Api.Run.load": true,
    "Public Api.Run.log_artifact": true,
    "Public Api.Run.logged_artifacts": true,
    "Public Api.Run.name": true,
    "Public Api.Run.path": true,
    "Public Api.Run.save": true,
    "Public Api.Run.scan_history": true,
    "Public Api.Run.snake_to_camel": true,
    "Public Api.Run.storage_id": true,
    "Public Api.Run.summary": true,
    "Public Api.Run.update": true,
    "Public Api.Run.upload_file": true,
    "Public Api.Run.url": true,
    "Public Api.Run.use_artifact": true,
    "Public Api.Run.used_artifacts": true,
    "Public Api.Run.username": true,
    "Public Api.Runs": false,
    "Public Api.Runs.QUERY": true,
    "Public Api.Runs.__eq__": true,
    "Public Api.Runs.__ge__": true,
    "Public Api.Runs.__getitem__": true,
    "Public Api.Runs.__gt__": true,
    "Public Api.Runs.__init__": true,
    "Public Api.Runs.__iter__": true,
    "Public Api.Runs.__le__": true,
    "Public Api.Runs.__len__": true,
    "Public Api.Runs.__lt__": true,
    "Public Api.Runs.__ne__": true,
    "Public Api.Runs.__new__": true,
    "Public Api.Runs.convert_objects": true,
    "Public Api.Runs.cursor": true,
    "Public Api.Runs.length": true,
    "Public Api.Runs.more": true,
    "Public Api.Runs.next": true,
    "Public Api.Runs.update_variables": true,
    "Public Api.Sweep": false,
    "Public Api.Sweep.QUERY": true,
    "Public Api.Sweep.__eq__": true,
    "Public Api.Sweep.__ge__": true,
    "Public Api.Sweep.__gt__": true,
    "Public Api.Sweep.__init__": true,
    "Public Api.Sweep.__le__": true,
    "Public Api.Sweep.__lt__": true,
    "Public Api.Sweep.__ne__": true,
    "Public Api.Sweep.__new__": true,
    "Public Api.Sweep.best_run": true,
    "Public Api.Sweep.config": true,
    "Public Api.Sweep.entity": true,
    "Public Api.Sweep.get": true,
    "Public Api.Sweep.load": true,
    "Public Api.Sweep.order": true,
    "Public Api.Sweep.path": true,
    "Public Api.Sweep.snake_to_camel": true,
    "Public Api.Sweep.url": true,
    "Public Api.Sweep.username": true
  },
  "py_module_names": [
    "Public Api"
  ],
  "site_link": null
}
